wait4it.py
wait4it-0.2.1.dist-info/LICENSE.md
wait4it-0.2.1.dist-info/METADATA
wait4it-0.2.1.dist-info/WHEEL
wait4it-0.2.1.dist-info/top_level.txt
wait4it-0.2.1.dist-info/RECORD
