Metadata-Version: 2.1
Name: wait4it
Version: 0.2.1
Summary: Wait until a certain TCP port is available
Home-page: https://github.com/David-Lor/python-wait4it/
Author: David-Lor
Author-email: 17401854+David-Lor@users.noreply.github.com
License: ISC
Download-URL: https://github.com/David-Lor/python-wait4it/archive/master.zip
Keywords: tcp,wait-for-it
Platform: UNKNOWN
Classifier: Development Status :: 4 - Beta
Classifier: Intended Audience :: Developers
Classifier: Topic :: Software Development :: Libraries
Classifier: License :: OSI Approved :: ISC License (ISCL)
Classifier: Programming Language :: Python :: 2
Classifier: Programming Language :: Python :: 2.7
Classifier: Programming Language :: Python :: 3
Classifier: Programming Language :: Python :: 3.4
Classifier: Programming Language :: Python :: 3.5
Classifier: Programming Language :: Python :: 3.6
Classifier: Programming Language :: Python :: 3.7
Classifier: Programming Language :: Python :: 3.8
